random_poems/__init__.py
random_poems/cli.py
random_poems/poems.py
random_poems-0.1.0.dist-info/METADATA
random_poems-0.1.0.dist-info/WHEEL
random_poems-0.1.0.dist-info/entry_points.txt
random_poems-0.1.0.dist-info/RECORD
